nodule-0.1.1.dist-info/METADATA
nodule-0.1.1.dist-info/WHEEL
nodule-0.1.1.dist-info/entry_points.txt
nodule-0.1.1.dist-info/licenses/COPYING
nodule-0.1.1.dist-info/licenses/LICENSES/Apache-2.0.txt
nodule-0.1.1.dist-info/licenses/LICENSES/CC-BY-4.0.txt
nodule-0.1.1.dist-info/licenses/LICENSES/CC-BY-SA-4.0.txt
nodule-0.1.1.dist-info/licenses/LICENSES/LicenseRef-DCO-1.1-license.txt
nodule/__init__.py
nodule/cli.py
nodule/nod.py
nodule-0.1.1.dist-info/RECORD
