Metadata-Version: 2.1
Name: nodule
Version: 0.1.1
Summary: Convert, visualize and iterate over heterogeneous trees.
Author-Email: David Seaward <david@librem.one>
License: Apache-2.0
Project-URL: Source, https://gitlab.com/lfdo/nodule
Project-URL: Project, https://lofidevops.neocities.org
Requires-Python: >=3.10
Requires-Dist: click>=8.1.7
Requires-Dist: ruamel-yaml-string>=0.1.1
Requires-Dist: tomlkit>=0.12.2
